Metadata-Version: 2.1
Name: MSO-WT
Version: 0.0.1
Summary: Official python implementation of the Maximal Spectral Overlap Wavelet Transform (MSO-WT)
Home-page: https://github.com/apostolosev/MSO_WT
Author: Apostolos Evangelidis
Author-email: apostolosev@gmail.com
License: UNKNOWN
Project-URL: Bug Tracker, https://github.com/apostolosev/MSO_WT/issues
Platform: UNKNOWN
Classifier: Programming Language :: Python :: 3
Classifier: License :: OSI Approved :: MIT License
Classifier: Operating System :: OS Independent
Requires-Python: >=3.6
